colorizedlog.py
colorizedlog-0.1.0.dist-info/DESCRIPTION.rst
colorizedlog-0.1.0.dist-info/METADATA
colorizedlog-0.1.0.dist-info/RECORD
colorizedlog-0.1.0.dist-info/WHEEL
colorizedlog-0.1.0.dist-info/metadata.json
colorizedlog-0.1.0.dist-info/top_level.txt
