Metadata-Version: 2.0
Name: colorizedlog
Version: 0.1.0
Summary: Replacement for logging.StreamHandler with colors.
Home-page: https://github.com/ZeeD26/colorizedlog
Author: Dominik Steinberger
Author-email: zeed.dev@icloud.com
License: BSD
Platform: UNKNOWN
Classifier: Development Status :: 3 - Alpha
Classifier: Intended Audience :: Developers
Classifier: License :: OSI Approved :: BSD License
Classifier: Programming Language :: Python :: 2
Classifier: Programming Language :: Python :: 2.7
Classifier: Programming Language :: Python :: 3
Classifier: Programming Language :: Python :: 3.4
Classifier: Programming Language :: Python :: 3.5
Classifier: Programming Language :: Python :: 3.6
Classifier: Topic :: System :: Logging
